pure_function_decorators/__init__.py
pure_function_decorators/enforce_deterministic.py
pure_function_decorators/forbid_globals.py
pure_function_decorators/forbid_side_effects.py
pure_function_decorators/immutable_arguments.py
pure_function_decorators/py.typed
pure_function_decorators/version.py
pure_function_decorators-0.1.4.dist-info/METADATA
pure_function_decorators-0.1.4.dist-info/WHEEL
pure_function_decorators-0.1.4.dist-info/licenses/LICENSE.md
pure_function_decorators-0.1.4.dist-info/RECORD
