Metadata-Version: 2.4
Name: pure-function-decorators
Version: 0.1.4
Summary: Try to enforce various types of function purity in Python
Project-URL: homepage, https://github.com/jlmcgraw/pure-function-decorators
Project-URL: source, https://github.com/jlmcgraw/pure-function-decorators
Project-URL: changelog, https://github.com/jlmcgraw/pure-function-decorators/blob/main/CHANGELOG.md
Author-email: Jesse McGraw <jlmcgraw@gmail.com>
License-File: LICENSE.md
Requires-Python: <4,>=3.12
